mroi_fd/__init__.py
mroi_fd/_utils.py
mroi_fd/face_detector.py
mroi_fd/routines.py
mroi_fd_amenji-0.0.4.dist-info/LICENSE
mroi_fd_amenji-0.0.4.dist-info/METADATA
mroi_fd_amenji-0.0.4.dist-info/WHEEL
mroi_fd_amenji-0.0.4.dist-info/top_level.txt
mroi_fd_amenji-0.0.4.dist-info/RECORD
