Metadata-Version: 2.1
Name: mroi-fd-amenji
Version: 0.0.4
Summary: A small example package
Home-page: https://gitlab.com/ailabuser/bacha-hybrid-mroi-face-detection
Author: ailab
Author-email: ailab@space.com
License: UNKNOWN
Platform: UNKNOWN
Classifier: Programming Language :: Python :: 3
Classifier: License :: OSI Approved :: MIT License
Classifier: Operating System :: OS Independent
Requires-Python: >=3.6
